legacai/__init__.py
tests/__init__.py
legaci-0.0.1.dist-info/METADATA
legaci-0.0.1.dist-info/WHEEL
legaci-0.0.1.dist-info/top_level.txt
legaci-0.0.1.dist-info/RECORD
