Metadata-Version: 2.1
Name: legaci
Version: 0.0.1
Summary: A library that might help you lift in your legacy into an ACI fabric
Home-page: https://github.com/johan-lahti/legaci
Author: Johan Lahti
Author-email: ccie60702@gmail.com
License: UNKNOWN
Platform: UNKNOWN
Classifier: Programming Language :: Python :: 3
Classifier: License :: OSI Approved :: MIT License
Classifier: Operating System :: OS Independent
Requires-Python: >=3.6
Requires-Dist: requests
Requires-Dist: tabulate
